perceval/backends/pontoon/__init__.py
perceval/backends/pontoon/_version.py
perceval/backends/pontoon/pontoon.py
perceval_pontoon-0.3.6.dist-info/METADATA
perceval_pontoon-0.3.6.dist-info/WHEEL
perceval_pontoon-0.3.6.dist-info/licenses/AUTHORS
perceval_pontoon-0.3.6.dist-info/licenses/LICENSE
perceval_pontoon-0.3.6.dist-info/RECORD
