Metadata-Version: 2.4
Name: perceval-pontoon
Version: 0.3.6
Summary: Perceval backend for Pontoon
License: GPL-3.0+
License-File: AUTHORS
License-File: LICENSE
Keywords: development,grimoirelab
Author: Bitergia Developers
Requires-Python: >=3.10,<4.0
Classifier: Development Status :: 4 - Beta
Classifier: Intended Audience :: Developers
Classifier: Intended Audience :: Science/Research
Classifier: License :: OSI Approved :: GNU General Public License v3 or later (GPLv3+)
Classifier: Programming Language :: Python :: 3
Classifier: Programming Language :: Python :: 3.10
Classifier: Programming Language :: Python :: 3.11
Classifier: Programming Language :: Python :: 3.12
Classifier: Programming Language :: Python :: 3.13
Classifier: Programming Language :: Python :: 3.14
Classifier: Topic :: Software Development
Requires-Dist: grimoirelab-toolkit (>=0.3)
Requires-Dist: perceval (>=0.19)
Project-URL: Bug Tracker, https://github.com/bitergia-analytics/grimoirelab-perceval-pontoon/issues
Project-URL: Homepage, https://chaoss.github.io/grimoirelab/
Project-URL: Repository, https://github.com/bitergia-analytics/grimoirelab-perceval-pontoon
